fedivis/__init__.py
fedivis/core.py
fedivis/core_base.py
fedivis/data_acquisition.py
fedivis/node.py
fedivis/node_manager.py
fedivis/release.py
fedivis/reply_graph_generator.py
fedivis/script.py
fedivis/settings.py
fedivis/utils.py
fedivis-0.1.2.dist-info/licenses/LICENSE
fedivis-0.1.2.dist-info/METADATA
fedivis-0.1.2.dist-info/WHEEL
fedivis-0.1.2.dist-info/entry_points.txt
fedivis-0.1.2.dist-info/top_level.txt
fedivis-0.1.2.dist-info/RECORD
